codearchiver/__init__.py
codearchiver/cli.py
codearchiver/core.py
codearchiver/storage.py
codearchiver/subprocess.py
codearchiver/version.py
codearchiver/modules/__init__.py
codearchiver/modules/git.py
codearchiver-1.1.dist-info/LICENSE
codearchiver-1.1.dist-info/METADATA
codearchiver-1.1.dist-info/WHEEL
codearchiver-1.1.dist-info/entry_points.txt
codearchiver-1.1.dist-info/top_level.txt
codearchiver-1.1.dist-info/RECORD
