Metadata-Version: 2.1
Name: codearchiver
Version: 1.1
Summary: A VCS repository archival tool
Author: JustAnotherArchivist
Project-URL: repository, https://gitea.arpa.li/JustAnotherArchivist/codearchiver
Classifier: Development Status :: 3 - Alpha
Classifier: License :: OSI Approved :: GNU General Public License v3 or later (GPLv3+)
Classifier: Programming Language :: Python :: 3.9
Classifier: Programming Language :: Python :: 3.10
Classifier: Programming Language :: Python :: 3.11
Requires-Python: ~=3.9
License-File: LICENSE
Requires-Dist: requests[socks]
Requires-Dist: filelock
